Metadata-Version: 2.1
Name: betterjson
Version: 0.0.0
Summary: An improved JSON-like format
Home-page: https://github.com/Starwort/betterjson
Author: Starwort
License: UNKNOWN
Platform: UNKNOWN
Classifier: Programming Language :: Python :: 3
Classifier: License :: OSI Approved :: MIT License
Classifier: Operating System :: OS Independent
Requires-Python: >=3.6
